{
  "source_file": "P05_v1.mp3",
  "language": "EN",
  "version": "standard",
  "page": "P05",
  "variant": "v1",
  "generated_at": "2026-03-06T07:26:53Z",
  "words": [
    {
      "word": "She",
      "start": 0.159,
      "end": 0.519,
      "type": "word"
    },
    {
      "word": "tasted",
      "start": 0.579,
      "end": 1.12,
      "type": "word"
    },
    {
      "word": "the",
      "start": 1.159,
      "end": 1.319,
      "type": "word"
    },
    {
      "word": "tiny",
      "start": 1.36,
      "end": 1.819,
      "type": "word"
    },
    {
      "word": "bowl.",
      "start": 1.86,
      "end": 2.639,
      "type": "word"
    },
    {
      "word": "\"This",
      "start": 2.639,
      "end": 2.899,
      "type": "word"
    },
    {
      "word": "one",
      "start": 2.98,
      "end": 3.159,
      "type": "word"
    },
    {
      "word": "is",
      "start": 3.24,
      "end": 3.679,
      "type": "word"
    },
    {
      "word": "just",
      "start": 4.539,
      "end": 4.96,
      "type": "word"
    },
    {
      "word": "right.\"",
      "start": 5.26,
      "end": 6.139,
      "type": "word"
    },
    {
      "word": "Goldie",
      "start": 6.179,
      "end": 6.699,
      "type": "word"
    },
    {
      "word": "ate",
      "start": 6.759,
      "end": 6.959,
      "type": "word"
    },
    {
      "word": "it",
      "start": 6.96,
      "end": 7.199,
      "type": "word"
    },
    {
      "word": "all",
      "start": 7.299,
      "end": 7.739,
      "type": "word"
    },
    {
      "word": "up,",
      "start": 7.819,
      "end": 8.26,
      "type": "word"
    },
    {
      "word": "every",
      "start": 8.38,
      "end": 8.819,
      "type": "word"
    },
    {
      "word": "last",
      "start": 8.84,
      "end": 9.279,
      "type": "word"
    },
    {
      "word": "drop",
      "start": 9.3,
      "end": 9.739,
      "type": "word"
    }
  ]
}