{
  "source_file": "P09_v1.mp3",
  "language": "EN",
  "version": "standard",
  "page": "P09",
  "variant": "v1",
  "generated_at": "2026-03-06T07:31:04Z",
  "words": [
    {
      "word": "Big",
      "start": 0.319,
      "end": 0.699,
      "type": "word"
    },
    {
      "word": "Bad",
      "start": 0.8,
      "end": 1.1,
      "type": "word"
    },
    {
      "word": "Wolf",
      "start": 1.199,
      "end": 1.559,
      "type": "word"
    },
    {
      "word": "took",
      "start": 1.679,
      "end": 1.899,
      "type": "word"
    },
    {
      "word": "a",
      "start": 1.98,
      "end": 2.099,
      "type": "word"
    },
    {
      "word": "deep",
      "start": 2.339,
      "end": 3.16,
      "type": "word"
    },
    {
      "word": "breath.",
      "start": 3.24,
      "end": 4.099,
      "type": "word"
    },
    {
      "word": "\"I'll",
      "start": 4.92,
      "end": 5.339,
      "type": "word"
    },
    {
      "word": "huff",
      "start": 5.48,
      "end": 5.939,
      "type": "word"
    },
    {
      "word": "and",
      "start": 6.46,
      "end": 6.659,
      "type": "word"
    },
    {
      "word": "I'll",
      "start": 6.759,
      "end": 6.899,
      "type": "word"
    },
    {
      "word": "puff",
      "start": 7.039,
      "end": 7.579,
      "type": "word"
    },
    {
      "word": "and",
      "start": 8.119,
      "end": 8.38,
      "type": "word"
    },
    {
      "word": "I'll",
      "start": 8.5,
      "end": 8.679,
      "type": "word"
    },
    {
      "word": "blow",
      "start": 8.84,
      "end": 9.5,
      "type": "word"
    },
    {
      "word": "your",
      "start": 9.619,
      "end": 9.8,
      "type": "word"
    },
    {
      "word": "house",
      "start": 9.92,
      "end": 10.279,
      "type": "word"
    },
    {
      "word": "down.\"",
      "start": 10.38,
      "end": 11.06,
      "type": "word"
    },
    {
      "word": "Crash!",
      "start": 11.84,
      "end": 13.039,
      "type": "word"
    },
    {
      "word": "Sticks",
      "start": 13.619,
      "end": 14.06,
      "type": "word"
    },
    {
      "word": "flew",
      "start": 14.159,
      "end": 14.619,
      "type": "word"
    },
    {
      "word": "everywhere.",
      "start": 14.719,
      "end": 15.48,
      "type": "word"
    },
    {
      "word": "That",
      "start": 15.819,
      "end": 16.02,
      "type": "word"
    },
    {
      "word": "house",
      "start": 16.079,
      "end": 16.379,
      "type": "word"
    },
    {
      "word": "was",
      "start": 16.42,
      "end": 16.56,
      "type": "word"
    },
    {
      "word": "gone",
      "start": 16.6,
      "end": 16.88,
      "type": "word"
    },
    {
      "word": "too.",
      "start": 16.899,
      "end": 17.359,
      "type": "word"
    },
    {
      "word": "Biggy",
      "start": 17.7,
      "end": 18.02,
      "type": "word"
    },
    {
      "word": "and",
      "start": 18.04,
      "end": 18.159,
      "type": "word"
    },
    {
      "word": "Woody",
      "start": 18.26,
      "end": 18.579,
      "type": "word"
    },
    {
      "word": "held",
      "start": 18.659,
      "end": 18.92,
      "type": "word"
    },
    {
      "word": "hands",
      "start": 19.039,
      "end": 19.379,
      "type": "word"
    },
    {
      "word": "and",
      "start": 19.399,
      "end": 19.52,
      "type": "word"
    },
    {
      "word": "ran",
      "start": 19.659,
      "end": 20.299,
      "type": "word"
    }
  ]
}