{
  "source_file": "P12_v1.mp3",
  "language": "EN",
  "version": "standard",
  "page": "P12",
  "variant": "v1",
  "generated_at": "2026-03-06T07:38:00Z",
  "words": [
    {
      "word": "Hops",
      "start": 0.079,
      "end": 0.459,
      "type": "word"
    },
    {
      "word": "arrived",
      "start": 0.5,
      "end": 1.059,
      "type": "word"
    },
    {
      "word": "panting",
      "start": 1.359,
      "end": 1.979,
      "type": "word"
    },
    {
      "word": "and",
      "start": 2.019,
      "end": 2.259,
      "type": "word"
    },
    {
      "word": "puffing.",
      "start": 2.339,
      "end": 2.839,
      "type": "word"
    },
    {
      "word": "\"You",
      "start": 3.139,
      "end": 3.419,
      "type": "word"
    },
    {
      "word": "were",
      "start": 3.439,
      "end": 3.619,
      "type": "word"
    },
    {
      "word": "amazing,\"",
      "start": 3.679,
      "end": 5.179,
      "type": "word"
    },
    {
      "word": "he",
      "start": 5.279,
      "end": 5.459,
      "type": "word"
    },
    {
      "word": "said.",
      "start": 5.519,
      "end": 5.819,
      "type": "word"
    },
    {
      "word": "\"I'll",
      "start": 6.079,
      "end": 6.419,
      "type": "word"
    },
    {
      "word": "never",
      "start": 6.46,
      "end": 6.819,
      "type": "word"
    },
    {
      "word": "be",
      "start": 6.859,
      "end": 7.059,
      "type": "word"
    },
    {
      "word": "lazy",
      "start": 7.119,
      "end": 7.559,
      "type": "word"
    },
    {
      "word": "again.\"",
      "start": 7.739,
      "end": 8.659,
      "type": "word"
    },
    {
      "word": "Tilly",
      "start": 8.8,
      "end": 9.14,
      "type": "word"
    },
    {
      "word": "smiled.",
      "start": 9.18,
      "end": 9.739,
      "type": "word"
    },
    {
      "word": "\"Wanna",
      "start": 10.139,
      "end": 10.399,
      "type": "word"
    },
    {
      "word": "run",
      "start": 10.44,
      "end": 10.619,
      "type": "word"
    },
    {
      "word": "together",
      "start": 10.639,
      "end": 10.96,
      "type": "word"
    },
    {
      "word": "next",
      "start": 11.039,
      "end": 11.3,
      "type": "word"
    },
    {
      "word": "time?\"",
      "start": 11.34,
      "end": 11.68,
      "type": "word"
    },
    {
      "word": "And",
      "start": 12.099,
      "end": 12.259,
      "type": "word"
    },
    {
      "word": "from",
      "start": 12.3,
      "end": 12.5,
      "type": "word"
    },
    {
      "word": "that",
      "start": 12.519,
      "end": 12.739,
      "type": "word"
    },
    {
      "word": "day",
      "start": 12.8,
      "end": 12.979,
      "type": "word"
    },
    {
      "word": "on,",
      "start": 13.099,
      "end": 13.619,
      "type": "word"
    },
    {
      "word": "they",
      "start": 13.679,
      "end": 13.84,
      "type": "word"
    },
    {
      "word": "became",
      "start": 13.88,
      "end": 14.479,
      "type": "word"
    },
    {
      "word": "the",
      "start": 14.56,
      "end": 14.699,
      "type": "word"
    },
    {
      "word": "very",
      "start": 14.779,
      "end": 15.079,
      "type": "word"
    },
    {
      "word": "best",
      "start": 15.259,
      "end": 15.659,
      "type": "word"
    },
    {
      "word": "of",
      "start": 15.739,
      "end": 15.88,
      "type": "word"
    },
    {
      "word": "friends.",
      "start": 15.96,
      "end": 16.459,
      "type": "word"
    }
  ]
}