{
  "source_file": "P02_v1.mp3",
  "language": "EN",
  "version": "toddler",
  "page": "P02",
  "variant": "v1",
  "generated_at": "2026-03-06T07:26:28Z",
  "words": [
    {
      "word": "Big",
      "start": 0.259,
      "end": 0.679,
      "type": "word"
    },
    {
      "word": "bowl",
      "start": 0.859,
      "end": 1.419,
      "type": "word"
    },
    {
      "word": "too",
      "start": 1.819,
      "end": 2.24,
      "type": "word"
    },
    {
      "word": "hot!",
      "start": 2.4,
      "end": 3.1,
      "type": "word"
    }
  ]
}